logfile_metrics/__init__.py
logfile_metrics/__main__.py
logfile_metrics/logfile_metrics.py
logfile_metrics-1.0.0.dist-info/METADATA
logfile_metrics-1.0.0.dist-info/WHEEL
logfile_metrics-1.0.0.dist-info/RECORD
